{
  "type_description_msg": {
    "type_description": {
      "type_name": "core_interfaces/action/PathPlanner_FeedbackMessage",
      "fields": [
        {
          "name": "goal_id",
          "type": {
            "type_id": 1,
            "capacity": 0,
            "string_capacity": 0,
            "nested_type_name": "unique_identifier_msgs/msg/UUID"
          },
          "default_value": ""
        },
        {
          "name": "feedback",
          "type": {
            "type_id": 1,
            "capacity": 0,
            "string_capacity": 0,
            "nested_type_name": "core_interfaces/action/PathPlanner_Feedback"
          },
          "default_value": ""
        }
      ]
    },
    "referenced_type_descriptions": [
      {
        "type_name": "core_interfaces/action/PathPlanner_Feedback",
        "fields": [
          {
            "name": "progress",
            "type": {
              "type_id": 6,
              "capacity": 0,
              "string_capacity": 0,
              "nested_type_name": ""
            },
            "default_value": ""
          }
        ]
      },
      {
        "type_name": "unique_identifier_msgs/msg/UUID",
        "fields": [
          {
            "name": "uuid",
            "type": {
              "type_id": 51,
              "capacity": 16,
              "string_capacity": 0,
              "nested_type_name": ""
            },
            "default_value": ""
          }
        ]
      }
    ]
  },
  "type_hashes": [
    {
      "type_name": "core_interfaces/action/PathPlanner_FeedbackMessage",
      "hash_string": "RIHS01_b94088440c8d8452f1b94bbb4a467c1ee2ab4d90838584430267b1be3251342d"
    },
    {
      "type_name": "core_interfaces/action/PathPlanner_Feedback",
      "hash_string": "RIHS01_2f992ffaaeea112022fc9fbedbfcee7908d3b31df2dbaa554d8da64f6271f822"
    },
    {
      "type_name": "unique_identifier_msgs/msg/UUID",
      "hash_string": "RIHS01_1b8e8aca958cbea28fe6ef60bf6c19b683c97a9ef60bb34752067d0f2f7ab437"
    }
  ]
}